src/__init__.py
src/osinfo.py
src/robot.py
dbartist-0.0.7.dist-info/LICENSE
dbartist-0.0.7.dist-info/METADATA
dbartist-0.0.7.dist-info/WHEEL
dbartist-0.0.7.dist-info/entry_points.txt
dbartist-0.0.7.dist-info/top_level.txt
dbartist-0.0.7.dist-info/RECORD
